MANIFEST.in
README.md
setup.py
biisan/__init__.py
biisan/biisan_settings.py
biisan/constants.py
biisan/generate.py
biisan/main.py
biisan/models.py
biisan/utils.py
biisan.egg-info/PKG-INFO
biisan.egg-info/SOURCES.txt
biisan.egg-info/dependency_links.txt
biisan.egg-info/not-zip-safe
biisan.egg-info/requires.txt
biisan.egg-info/top_level.txt
biisan/directives/__init__.py
biisan/processors/__init__.py
biisan/templates/base.html
biisan/templates/blog_archive.html
biisan/templates/blog_top.html
biisan/templates/index.html
biisan/templates/rss20.xml
biisan/templates/sitemaps.xml
biisan/templates/components/about.html
biisan/templates/components/blockquote.html
biisan/templates/components/bulletlist.html
biisan/templates/components/caption.html
biisan/templates/components/colspec.html
biisan/templates/components/definitionlist.html
biisan/templates/components/definitionlistitem.html
biisan/templates/components/emphasis.html
biisan/templates/components/entry.html
biisan/templates/components/enumeratedlist.html
biisan/templates/components/figure.html
biisan/templates/components/header_row.html
biisan/templates/components/image.html
biisan/templates/components/listitem.html
biisan/templates/components/literalblock.html
biisan/templates/components/note.html
biisan/templates/components/paragraph.html
biisan/templates/components/raw.html
biisan/templates/components/reference.html
biisan/templates/components/row.html
biisan/templates/components/section.html
biisan/templates/components/story.html
biisan/templates/components/story_extra_bottom.html
biisan/templates/components/story_extra_headers.html
biisan/templates/components/story_extra_top1.html
biisan/templates/components/story_extra_top2.html
biisan/templates/components/strong.html
biisan/templates/components/substitutiondefinition.html
biisan/templates/components/table.html
biisan/templates/components/target.html
biisan/templates/components/tbody.html
biisan/templates/components/tgroup.html
biisan/templates/components/thead.html
biisan/templates/components/topic.html
biisan/templates/components/transition.html
requirements/requirements.txt