Metadata-Version: 2.1
Name: biisan
Version: 0.8.2
Summary: Static site generator.
Home-page: https://github.com/tsuyukimakoto/biisan
Author: makoto tsuyuki
Author-email: mtsuyuki@gmail.com
License: UNKNOWN
Keywords: static site generator,docutils,customizable
Platform: UNKNOWN
Classifier: Development Status :: 4 - Beta
Classifier: Environment :: Console
Classifier: Intended Audience :: End Users/Desktop
Classifier: License :: OSI Approved :: MIT License
Classifier: Operating System :: MacOS :: MacOS X
Classifier: Operating System :: POSIX
Classifier: Operating System :: Unix
Classifier: Programming Language :: Python
Classifier: Programming Language :: Python :: 3.5
Classifier: Programming Language :: Python :: 3.6
Classifier: Programming Language :: Python :: 3.7
Classifier: Programming Language :: Python :: 3.8
Classifier: Topic :: Documentation
